fcm_django/__init__.py
fcm_django/admin.py
fcm_django/apps.py
fcm_django/fields.py
fcm_django/models.py
fcm_django/settings.py
fcm_django/api/__init__.py
fcm_django/api/rest_framework.py
fcm_django/api/tastypie.py
fcm_django/migrations/0001_initial.py
fcm_django/migrations/0002_auto_20160808_1645.py
fcm_django/migrations/0003_auto_20170313_1314.py
fcm_django/migrations/0004_auto_20181128_1642.py
fcm_django/migrations/0005_auto_20170808_1145.py
fcm_django/migrations/0006_auto_20210802_1140.py
fcm_django/migrations/0007_auto_20211001_1440.py
fcm_django/migrations/0008_auto_20211224_1205.py
fcm_django/migrations/__init__.py
fcm_django-1.0.9.dist-info/LICENSE.txt
fcm_django-1.0.9.dist-info/METADATA
fcm_django-1.0.9.dist-info/WHEEL
fcm_django-1.0.9.dist-info/top_level.txt
fcm_django-1.0.9.dist-info/RECORD
