Metadata-Version: 1.2
Name: fcm-django
Version: 1.0.9
Summary: Send push notifications to mobile devices & browsers through FCM in Django.
Home-page: https://github.com/xtrinch/fcm-django
Author: xTrinch
Author-email: mojca.rojko@gmail.com
License: UNKNOWN
Download-URL: https://github.com/xtrinch/fcm-django/tarball/master
Platform: UNKNOWN
Classifier: Development Status :: 5 - Production/Stable
Classifier: Environment :: Web Environment
Classifier: Framework :: Django
Classifier: Intended Audience :: Developers
Classifier: License :: OSI Approved :: MIT License
Classifier: Programming Language :: Python
Classifier: Programming Language :: Python :: 3
Classifier: Programming Language :: Python :: 3.6
Classifier: Programming Language :: Python :: 3.7
Classifier: Programming Language :: Python :: 3.8
Classifier: Programming Language :: Python :: 3.9
Classifier: Topic :: Software Development :: Libraries :: Python Modules
Classifier: Topic :: System :: Networking
Requires-Python: >=3
